{"cameraMode":{"drawMode":0,"name":"Shaded","section":"Shading Mode"},"sceneLighting":true,"audioPlay":false,"sceneViewState":{"m_AlwaysRefresh":false,"showFog":true,"showSkybox":true,"showFlares":true,"showImageEffects":true,"showParticleSystems":true,"showVisualEffectGraphs":true,"m_FxEnabled":true},"in2DMode":false,"pivot":{"x":-19.74295425415039,"y":12.825677871704102,"z":-58.33648681640625},"rotation":{"x":-0.5171539187431336,"y":-0.03079715371131897,"z":0.018556496128439904,"w":-0.8551641702651978},"size":99.47911834716797,"orthographic":false}